person_local/__init__.py
person_local/person.py
person_local/persons_local.py
person_local-0.0.82.dist-info/METADATA
person_local-0.0.82.dist-info/WHEEL
person_local-0.0.82.dist-info/top_level.txt
person_local-0.0.82.dist-info/RECORD
