Metadata-Version: 2.4
Name: person-local
Version: 0.0.82
Summary: PyPI Package for Circles person Local Python
Home-page: https://github.com/circles-zone/person-local-python-package
Author: Circles
Author-email: info@circlez.ai
Classifier: Programming Language :: Python :: 3
Classifier: License :: Other/Proprietary License
Classifier: Operating System :: OS Independent
Requires-Dist: database-mysql-local>=0.0.359
Requires-Dist: language-remote>=0.0.20
Requires-Dist: logger-local>=0.0.135
Requires-Dist: user-context-remote>=0.0.75
Requires-Dist: people-local>=0.0.17
Dynamic: author
Dynamic: author-email
Dynamic: classifier
Dynamic: description
Dynamic: description-content-type
Dynamic: home-page
Dynamic: requires-dist
Dynamic: summary
